PopoutApps/__init__.py
PopoutApps/qucs-netlist.dat
PopoutApps/qucs-netlist.hlp
PopoutApps/qucs-netlist.py
qucs_netlist-0.0.5.dist-info/LICENSE
qucs_netlist-0.0.5.dist-info/METADATA
qucs_netlist-0.0.5.dist-info/WHEEL
qucs_netlist-0.0.5.dist-info/top_level.txt
qucs_netlist-0.0.5.dist-info/RECORD
