Metadata-Version: 2.1
Name: qucs-netlist
Version: 0.0.5
Summary: Converts Qucs schematic files into a form suitable for a PCB design application.
Home-page: https://github.com/PopoutApps/qucs-netlist
Author: Chris Rogers
Author-email: popout.apps@yahoo.com
License: UNKNOWN
Project-URL: Bug Tracker, https://github.com/PopoutApps/qucs-netlist/issues
Platform: UNKNOWN
Classifier: Programming Language :: Python :: 3
Classifier: License :: OSI Approved :: MIT License
Classifier: Operating System :: OS Independent
Requires-Python: >=3.7
License-File: LICENSE
